snakemake_logger_plugin_pypsa/__init__.py
snakemake_logger_plugin_pypsa-0.1.0.dist-info/METADATA
snakemake_logger_plugin_pypsa-0.1.0.dist-info/WHEEL
snakemake_logger_plugin_pypsa-0.1.0.dist-info/entry_points.txt
snakemake_logger_plugin_pypsa-0.1.0.dist-info/top_level.txt
snakemake_logger_plugin_pypsa-0.1.0.dist-info/RECORD
