Metadata-Version: 2.4
Name: snakemake-logger-plugin-pypsa
Version: 0.1.0
Summary: A PyPSA-Eur logger plugin for Snakemake
Author-email: PyPSA-Eur Contributors <will.usher@openenergytransition.org>
License: MIT
Requires-Python: >=3.10
Requires-Dist: snakemake-interface-logger-plugins>=1.2.0
